{ "height":20,
 "layers":[
        {
         "data":[0, 0, 0, 0, 0, 0, 0, 0, 0, 0, 11, 11, 11, 11, 11, 11, 11, 11, 11, 11, 11, 11, 11, 11, 11, 11, 11, 11, 11, 11, 11, 11, 11, 0, 0, 0, 0, 0, 0, 0, 0, 0, 0, 0, 0, 0, 0, 0, 0, 0, 11, 26, 26, 26, 26, 26, 26, 26, 26, 26, 26, 26, 26, 26, 26, 26, 26, 26, 26, 26, 26, 26, 11, 0, 0, 0, 0, 0, 0, 0, 0, 0, 0, 0, 0, 0, 0, 0, 0, 0, 11, 26, 26, 26, 26, 26, 26, 26, 26, 26, 26, 26, 26, 26, 26, 26, 26, 26, 26, 26, 26, 26, 11, 0, 0, 0, 0, 0, 0, 0, 0, 0, 0, 0, 0, 0, 0, 0, 0, 0, 11, 26, 26, 26, 26, 26, 26, 26, 26, 26, 26, 26, 26, 26, 26, 26, 26, 26, 26, 26, 26, 26, 11, 0, 0, 0, 0, 0, 0, 0, 0, 0, 0, 0, 0, 0, 0, 0, 0, 0, 11, 26, 26, 26, 26, 26, 26, 26, 26, 26, 26, 26, 26, 26, 26, 26, 26, 26, 26, 26, 26, 26, 11, 0, 0, 0, 0, 0, 0, 0, 0, 0, 0, 0, 0, 0, 0, 0, 0, 0, 11, 26, 26, 26, 26, 26, 26, 26, 26, 26, 26, 26, 26, 26, 26, 26, 26, 26, 26, 26, 26, 26, 11, 0, 0, 0, 0, 0, 0, 0, 0, 0, 0, 0, 0, 0, 0, 0, 0, 0, 11, 26, 26, 26, 26, 26, 26, 26, 26, 26, 26, 26, 26, 26, 26, 26, 26, 26, 26, 26, 26, 26, 11, 0, 0, 0, 0, 0, 0, 0, 0, 0, 0, 0, 0, 0, 0, 0, 0, 0, 2, 26, 26, 26, 26, 26, 26, 26, 26, 26, 26, 26, 26, 26, 26, 26, 26, 26, 26, 26, 26, 26, 11, 0, 0, 0, 0, 0, 0, 0, 0, 0, 0, 0, 0, 0, 0, 0, 0, 0, 2, 26, 26, 26, 26, 26, 26, 26, 26, 26, 26, 26, 26, 26, 26, 26, 26, 26, 26, 26, 26, 26, 11, 0, 0, 0, 0, 0, 0, 0, 0, 0, 0, 0, 0, 0, 0, 0, 0, 0, 2, 26, 26, 26, 26, 26, 26, 26, 26, 26, 26, 26, 26, 26, 26, 26, 26, 26, 26, 26, 26, 26, 11, 0, 0, 0, 0, 0, 0, 0, 0, 0, 0, 0, 0, 0, 0, 0, 0, 0, 2, 26, 26, 26, 26, 26, 26, 26, 26, 26, 26, 26, 26, 26, 26, 26, 26, 26, 26, 26, 26, 26, 11, 0, 0, 0, 0, 0, 0, 0, 0, 0, 0, 0, 0, 0, 0, 0, 0, 0, 2, 26, 26, 26, 26, 26, 26, 26, 26, 26, 26, 26, 26, 26, 26, 26, 26, 26, 26, 26, 26, 26, 11, 0, 0, 0, 0, 0, 0, 0, 0, 0, 0, 0, 0, 0, 0, 0, 0, 0, 2, 26, 26, 26, 26, 26, 26, 26, 26, 26, 26, 26, 26, 26, 26, 26, 26, 26, 26, 26, 26, 26, 11, 0, 0, 0, 0, 0, 0, 0, 0, 0, 0, 0, 0, 0, 0, 0, 0, 0, 2, 26, 26, 26, 26, 26, 26, 26, 26, 26, 26, 26, 26, 26, 26, 26, 26, 26, 26, 26, 26, 26, 11, 0, 0, 0, 0, 0, 0, 0, 0, 0, 0, 0, 0, 0, 0, 0, 0, 0, 2, 26, 26, 26, 26, 26, 26, 26, 26, 26, 26, 26, 26, 26, 26, 26, 26, 26, 26, 26, 26, 26, 11, 0, 0, 0, 0, 0, 0, 0, 0, 0, 0, 0, 0, 0, 0, 0, 0, 0, 2, 26, 26, 26, 26, 26, 26, 26, 26, 26, 26, 1, 26, 26, 26, 26, 26, 26, 26, 26, 26, 26, 11, 0, 0, 0, 0, 0, 0, 0, 0, 0, 0, 0, 0, 0, 0, 0, 0, 0, 2, 26, 26, 26, 26, 26, 26, 26, 26, 26, 26, 26, 26, 26, 26, 26, 26, 26, 26, 26, 26, 26, 11, 0, 0, 0, 0, 0, 0, 0, 0, 0, 0, 0, 0, 0, 0, 0, 0, 0, 2, 2, 2, 2, 2, 2, 2, 2, 2, 2, 2, 2, 2, 2, 11, 11, 11, 11, 11, 11, 11, 11, 11, 0, 0, 0, 0, 0, 0, 0, 0, 0, 0, 0, 0, 0, 0, 0, 0, 0, 0, 0, 0, 0, 0, 0, 0, 0, 0, 0, 0, 0, 0, 0, 0, 0, 0, 0, 0, 0, 0, 0, 0, 0, 0, 0, 0, 0, 0, 0, 0, 0, 0, 0, 0, 0, 0, 0, 0, 0, 0, 0, 0, 0, 0, 0, 0, 0, 0, 0, 0, 0, 0, 0, 0, 0, 0, 0, 0, 0, 0, 0, 0, 0, 0, 0, 0, 0, 0, 0],
         "height":20,
         "name":"Tile Layer 1",
         "opacity":1,
         "type":"tilelayer",
         "visible":true,
         "width":40,
         "x":0,
         "y":0
        }],
 "nextobjectid":1,
 "orientation":"orthogonal",
 "renderorder":"right-down",
 "tiledversion":"1.0.3",
 "tileheight":16,
 "tilesets":[
        {
         "columns":0,
         "firstgid":1,
         "grid":
            {
             "height":1,
             "orientation":"orthogonal",
             "width":1
            },
         "margin":0,
         "name":"zzz",
         "spacing":0,
         "tilecount":26,
         "tileheight":45,
         "tiles":
            {
             "0":
                {
                 "image":"..\/gfx\/base\/OBHero.png",
                 "imageheight":34,
                 "imagewidth":16
                },
             "1":
                {
                 "image":"..\/gfx\/base\/decoration\/ground.png",
                 "imageheight":16,
                 "imagewidth":16
                },
             "10":
                {
                 "image":"..\/gfx\/base\/decoration\/ground.png",
                 "imageheight":16,
                 "imagewidth":16
                },
             "11":
                {
                 "image":"..\/gfx\/base\/decoration\/ground_lr2.png",
                 "imageheight":16,
                 "imagewidth":16
                },
             "12":
                {
                 "image":"..\/gfx\/base\/decoration\/ground_lr.png",
                 "imageheight":16,
                 "imagewidth":16
                },
             "13":
                {
                 "image":"..\/gfx\/base\/decoration\/ground_gray_brick.png",
                 "imageheight":16,
                 "imagewidth":16
                },
             "14":
                {
                 "image":"..\/gfx\/base\/decoration\/fireball_small.png",
                 "imageheight":5,
                 "imagewidth":5
                },
             "15":
                {
                 "image":"..\/gfx\/base\/decoration\/explosion_small.png",
                 "imageheight":10,
                 "imagewidth":10
                },
             "16":
                {
                 "image":"..\/gfx\/base\/decoration\/doggy.png",
                 "imageheight":16,
                 "imagewidth":16
                },
             "17":
                {
                 "image":"..\/gfx\/base\/decoration\/button_floor.png",
                 "imageheight":7,
                 "imagewidth":16
                },
             "18":
                {
                 "image":"..\/gfx\/base\/decoration\/button_floor_pressed.png",
                 "imageheight":5,
                 "imagewidth":16
                },
             "19":
                {
                 "image":"..\/gfx\/base\/decoration\/brick_gray_bg.png",
                 "imageheight":16,
                 "imagewidth":16
                },
             "2":
                {
                 "image":"..\/gfx\/base\/OBFireSource.png",
                 "imageheight":14,
                 "imagewidth":13
                },
             "20":
                {
                 "image":"..\/gfx\/base\/decoration\/block_pushable.png",
                 "imageheight":16,
                 "imagewidth":16
                },
             "21":
                {
                 "image":"..\/gfx\/base\/decoration\/block_falling_yellow.png",
                 "imageheight":8,
                 "imagewidth":8
                },
             "22":
                {
                 "image":"..\/gfx\/base\/decoration\/block_fall_on_touch.png",
                 "imageheight":16,
                 "imagewidth":16
                },
             "23":
                {
                 "image":"..\/gfx\/base\/decoration\/block_fall_on_touch_damaged.png",
                 "imageheight":16,
                 "imagewidth":16
                },
             "24":
                {
                 "image":"..\/gfx\/base\/decoration\/block_fall_on_touch_damaged_02.png",
                 "imageheight":16,
                 "imagewidth":16
                },
             "25":
                {
                 "image":"..\/gfx\/base\/OBBall.png",
                 "imageheight":8,
                 "imagewidth":8
                },
             "3":
                {
                 "image":"..\/gfx\/base\/OBFireball.png",
                 "imageheight":8,
                 "imagewidth":8
                },
             "4":
                {
                 "image":"..\/gfx\/base\/decoration\/vampire_wannabe.png",
                 "imageheight":16,
                 "imagewidth":16
                },
             "5":
                {
                 "image":"..\/gfx\/base\/decoration\/star_yellow.png",
                 "imageheight":45,
                 "imagewidth":50
                },
             "6":
                {
                 "image":"..\/gfx\/base\/decoration\/spring_jump_up.png",
                 "imageheight":10,
                 "imagewidth":16
                },
             "7":
                {
                 "image":"..\/gfx\/base\/decoration\/spring_jump_up_extended.png",
                 "imageheight":16,
                 "imagewidth":16
                },
             "8":
                {
                 "image":"..\/gfx\/base\/decoration\/spike_ceiling.png",
                 "imageheight":16,
                 "imagewidth":16
                },
             "9":
                {
                 "image":"..\/gfx\/base\/decoration\/spike_ceiling_falling.png",
                 "imageheight":16,
                 "imagewidth":16
                }
            },
         "tilewidth":50
        }],
 "tilewidth":16,
 "type":"map",
 "version":1,
 "width":40
}